DbReactCreator/__init__.py
DbReactCreator/admin.py
DbReactCreator/apps.py
DbReactCreator/models.py
DbReactCreator/reactDecorators.py
DbReactCreator/reactMiddle.py
DbReactCreator/migrations/__init__.py
django_dbreact-0.3.dist-info/DESCRIPTION.rst
django_dbreact-0.3.dist-info/METADATA
django_dbreact-0.3.dist-info/RECORD
django_dbreact-0.3.dist-info/WHEEL
django_dbreact-0.3.dist-info/metadata.json
django_dbreact-0.3.dist-info/top_level.txt
